pyldsdk/__init__.py
pyldsdk/main.py
pyldsdk/types.py
pyldsdk-0.0.2.dist-info/LICENSE
pyldsdk-0.0.2.dist-info/METADATA
pyldsdk-0.0.2.dist-info/WHEEL
pyldsdk-0.0.2.dist-info/top_level.txt
pyldsdk-0.0.2.dist-info/RECORD
