Metadata-Version: 2.1
Name: pyldsdk
Version: 0.0.2
Summary: Python Logix Designer SDK
Author-email: aawilliams85 <adair.williams85@gmail.com>
License: MIT License
Project-URL: Repository, https://github.com/aawilliams85/pyldsdk.git
License-File: LICENSE
Requires-Dist: pythonnet
